<?xml version="1.0" encoding="utf-8"?>
<LanguageInfo>
  <friendlyNameNative>Deutsch</friendlyNameNative>
  <friendlyNameEnglish>German</friendlyNameEnglish>
  <canBeTiny>true</canBeTiny>
  <languageWorkerClass>LanguageWorker_German</languageWorkerClass>
  <credits>
    <li Class="CreditRecord_Role">
      <roleKey>Credit_Translator</roleKey>
      <creditee>Markus 'Haplo' Keuneke</creditee>
    </li>
    <li Class="CreditRecord_Role">
      <roleKey>Credit_Translator</roleKey>
      <creditee>Dominik 'TheEisbaer'</creditee>
    </li>
    <li Class="CreditRecord_Role">
      <roleKey>Credit_Translator</roleKey>
      <creditee>Alex 'TeiXeR' Weiß</creditee>
    </li>
    <li Class="CreditRecord_Role">
      <roleKey>Credit_Translator</roleKey>
      <creditee>Ragnar-F</creditee>
    </li>
  </credits>
</LanguageInfo>
